setup.py
Topsis_ArnavAgarwal_102203985.egg-info/PKG-INFO
Topsis_ArnavAgarwal_102203985.egg-info/SOURCES.txt
Topsis_ArnavAgarwal_102203985.egg-info/dependency_links.txt
Topsis_ArnavAgarwal_102203985.egg-info/requires.txt
Topsis_ArnavAgarwal_102203985.egg-info/top_level.txt
topsis/__init__.py