Metadata-Version: 2.2
Name: Topsis-ArnavAgarwal-102203985
Version: 1.0.0
Summary: A Python package for performing TOPSIS analysis.
Home-page: https://github.com/Teddyy27/Topsis-ArnavAgarwal-102203985
Author: Arnav Agarwal
Author-email: arnavagarwal123654@gmail.com
Classifier: Programming Language :: Python :: 3
Classifier: License :: OSI Approved :: MIT License
Classifier: Operating System :: OS Independent
Requires-Python: >=3.6
Requires-Dist: pandas
Requires-Dist: numpy
Requires-Dist: openpyxl
Dynamic: author
Dynamic: author-email
Dynamic: classifier
Dynamic: description
Dynamic: description-content-type
Dynamic: home-page
Dynamic: requires-dist
Dynamic: requires-python
Dynamic: summary
